credit_risk/__init__.py
credit_risk/cli.py
credit_risk/config.py
credit_risk/exceptions.py
credit_risk/logging_config.py
credit_risk/py.typed
credit_risk/core/__init__.py
credit_risk/core/application.py
credit_risk/core/economic.py
credit_risk/models/__init__.py
credit_risk/models/base.py
credit_risk/models/corporate.py
credit_risk/models/individual.py
credit_risk/utils/__init__.py
credit_risk_creditum-2.1.1.dist-info/METADATA
credit_risk_creditum-2.1.1.dist-info/WHEEL
credit_risk_creditum-2.1.1.dist-info/entry_points.txt
credit_risk_creditum-2.1.1.dist-info/top_level.txt
credit_risk_creditum-2.1.1.dist-info/RECORD
