Metadata-Version: 2.4
Name: credit-risk-creditum
Version: 2.1.1
Summary: Advanced credit risk assessment and stress testing with real-time economic data integration
Home-page: https://github.com/credit-risk-creditum/creditum
Author: Omoshola Owolabi
Author-email: Omoshola Owolabi <owolabi.omoshola@outlook.com>
Maintainer-email: Omoshola Owolabi <owolabi.omoshola@outlook.com>
License: MIT
Project-URL: Homepage, https://github.com/credit-risk-creditum/creditum
Project-URL: Documentation, https://github.com/credit-risk-creditum/creditum#documentation
Project-URL: Repository, https://github.com/credit-risk-creditum/creditum
Project-URL: Bug Reports, https://github.com/credit-risk-creditum/creditum/issues
Project-URL: PyPI, https://pypi.org/project/credit-risk-creditum/
Keywords: credit,risk,assessment,fintech,machine-learning,stress-testing,economic-data
Classifier: Development Status :: 4 - Beta
Classifier: Intended Audience :: Financial and Insurance Industry
Classifier: Intended Audience :: Developers
Classifier: Topic :: Office/Business :: Financial :: Investment
Classifier: Topic :: Scientific/Engineering :: Information Analysis
Classifier: License :: OSI Approved :: MIT License
Classifier: Operating System :: OS Independent
Classifier: Programming Language :: Python :: 3
Classifier: Programming Language :: Python :: 3.8
Classifier: Programming Language :: Python :: 3.9
Classifier: Programming Language :: Python :: 3.10
Classifier: Programming Language :: Python :: 3.11
Classifier: Programming Language :: Python :: 3.12
Requires-Python: >=3.8
Requires-Dist: numpy<2.0.0,>=1.21.0
Requires-Dist: pandas>=1.3.0
Requires-Dist: scikit-learn>=1.0.0
Requires-Dist: requests>=2.25.0
Requires-Dist: typing-extensions>=4.0.0
Provides-Extra: dev
Requires-Dist: pytest>=7.0.0; extra == "dev"
Requires-Dist: pytest-cov>=4.0.0; extra == "dev"
Requires-Dist: black>=23.0.0; extra == "dev"
Requires-Dist: flake8>=6.0.0; extra == "dev"
Requires-Dist: mypy>=1.0.0; extra == "dev"
Requires-Dist: pre-commit>=3.0.0; extra == "dev"
Provides-Extra: docs
Requires-Dist: sphinx>=6.0.0; extra == "docs"
Requires-Dist: sphinx-rtd-theme>=1.2.0; extra == "docs"
Requires-Dist: myst-parser>=1.0.0; extra == "docs"
Provides-Extra: test
Requires-Dist: pytest>=7.0.0; extra == "test"
Requires-Dist: pytest-cov>=4.0.0; extra == "test"
Requires-Dist: pytest-mock>=3.10.0; extra == "test"
Dynamic: author
Dynamic: home-page
Dynamic: requires-python
